pypicgo/__init__.py
pypicgo/upload.py
pypicgo/core/__init__.py
pypicgo/core/config.py
pypicgo/core/exceptions.py
pypicgo/core/execute.py
pypicgo/core/logger.py
pypicgo/core/base/__init__.py
pypicgo/core/base/file.py
pypicgo/core/base/plugin.py
pypicgo/core/base/result.py
pypicgo/core/base/uploader.py
pypicgo/core/models/__init__.py
pypicgo/core/utils/__init__.py
pypicgo/core/utils/modules.py
pypicgo/plugins/__init__.py
pypicgo/plugins/clipboard/__init__.py
pypicgo/plugins/clipboard/clipbrd.py
pypicgo/plugins/compress/__init__.py
pypicgo/plugins/jsdelivr/__init__.py
pypicgo/plugins/notify/__init__.py
pypicgo/plugins/notify/tk.py
pypicgo/plugins/rename/__init__.py
pypicgo/plugins/typora/__init__.py
pypicgo/uploaders/__init__.py
pypicgo/uploaders/gitee/__init__.py
pypicgo/uploaders/gitee/schemas.py
pypicgo/uploaders/gitee/uploader.py
pypicgo/uploaders/github/__init__.py
pypicgo/uploaders/github/schemas.py
pypicgo/uploaders/github/uploader.py
pypicgo/uploaders/qiniu/__init__.py
pypicgo/uploaders/qiniu/schemas.py
pypicgo/uploaders/qiniu/uploader.py
pypicgo/uploaders/qiniu/utils.py
pypicgo/uploaders/smms/__init__.py
pypicgo/uploaders/smms/uploader.py
pypicgo-1.1.2.dist-info/LICENSE
pypicgo-1.1.2.dist-info/METADATA
pypicgo-1.1.2.dist-info/WHEEL
pypicgo-1.1.2.dist-info/entry_points.txt
pypicgo-1.1.2.dist-info/top_level.txt
pypicgo-1.1.2.dist-info/RECORD
