Metadata-Version: 2.1
Name: pypicgo
Version: 1.1.2
Summary: A simple & powerful tool for pictures uploading built by python
Home-page: https://github.com/AnsGoo/PyPicGo
Author: ansgoo
Author-email: haiven_123@163.com
License: MIT Licence
Keywords: python,pypicgo
Platform: any
Classifier: Development Status :: 5 - Production/Stable
Classifier: Programming Language :: Python
Classifier: Programming Language :: Python :: 3
Classifier: Programming Language :: Python :: 3 :: Only
Classifier: Programming Language :: Python :: 3.6
Classifier: Programming Language :: Python :: 3.7
Classifier: Programming Language :: Python :: 3.8
Classifier: Programming Language :: Python :: 3.9
Classifier: License :: OSI Approved :: MIT License
Classifier: Operating System :: Unix
Classifier: Operating System :: POSIX :: Linux
Classifier: Environment :: Console
Classifier: Environment :: MacOS X
License-File: LICENSE
Requires-Dist: pydantic (>=1.7.4)
Requires-Dist: pyyaml (>=5.3.1)
Requires-Dist: requests (>=2.22.0)
Requires-Dist: requests-toolbelt (>=0.9.1)
Requires-Dist: Pillow (>=8.2.0)
Requires-Dist: pyperclip (>=1.8.0)
